{
    "backend": "api-server-django",
    "db_name": "",
    "db_pass": "",
    "db_type": "sqlite",
    "db_user": "",
    "dbms": "1",
    "description": "generated product",
    "design": "material-kit",
    "docker": "1",
    "err_code": 0,
    "frontend": "react",
    "heroku": "0",
    "pattern": "fullstack",
    "pro": "0",
    "task_id": "29999f55-94a2-4dc4-b659-a62037bd4676",
    "task_info": "Upload Sources [0%] - 347 files",
    "task_output": "29999f55-94a2-4dc4-b659-a62037bd4676.zip",
    "task_result": "SUCCESS",
    "task_state": "RUNNING",
    "task_ts_end": "2024-11-12-13-30-32",
    "task_ts_start": "2024-11-12-13-30-30"
}